{
	"addAttachment": "/jaxrs/attachment",
	"listAttachment": "/jaxrs/attachment/folder/{id}/sub/direct",
	"listAttachmentTop": "/jaxrs/attachment/list/top",
	"getAttachment": "/jaxrs/attachment/{id}",
	"removeAttachment": "/jaxrs/attachment/{id}",
	"updateAttachment": "/jaxrs/attachment/{id}",
	"renameAttachment": "/jaxrs/attachment/{id}/rename",
	"shareAttachment": "/jaxrs/attachment/{id}/share/add/{people}",
	"claerShareAttachment": "/jaxrs/attachment/{id}/share/clear",
	"removeShareAttachment": "/jaxrs/attachment/{id}/share/remove/{people}",
	
	"addFolder": "/jaxrs/folder",
	"listFolderTop": "/jaxrs/folder/list/top",
	"getFolder": "/jaxrs/folder/{id}",
	"removeFolder": "/jaxrs/folder/{id}",
	"renameFolder": "/jaxrs/folder/{id}",
	"listFolder": "/jaxrs/folder/{id}/sub/direct"
}